LICENSE.md
MANIFEST.in
README.md
pyproject.toml
setup.py
pyofm/__init__.py
pyofm/pyOFM.py
pyofm_orion.egg-info/PKG-INFO
pyofm_orion.egg-info/SOURCES.txt
pyofm_orion.egg-info/dependency_links.txt
pyofm_orion.egg-info/not-zip-safe
pyofm_orion.egg-info/requires.txt
pyofm_orion.egg-info/top_level.txt
src/Allclean
src/Allmake
src/OFMesh.C
src/OFMesh.H
src/pyOFMesh.pyx
src/setArgs.H
src/setRootCasePython.H
src/setup.py
src/Make/files
src/Make/options